dcm2bids/__init__.py
dcm2bids/acquisition.py
dcm2bids/dcm2bids_gen.py
dcm2bids/dcm2niix_gen.py
dcm2bids/participant.py
dcm2bids/sidecar.py
dcm2bids/version.py
dcm2bids/cli/__init__.py
dcm2bids/cli/dcm2bids.py
dcm2bids/cli/dcm2bids_helper.py
dcm2bids/cli/dcm2bids_scaffold.py
dcm2bids/utils/__init__.py
dcm2bids/utils/args.py
dcm2bids/utils/io.py
dcm2bids/utils/logger.py
dcm2bids/utils/scaffold.py
dcm2bids/utils/tools.py
dcm2bids/utils/utils.py
dcm2bids-3.2.0.dist-info/LICENSE.txt
dcm2bids-3.2.0.dist-info/METADATA
dcm2bids-3.2.0.dist-info/WHEEL
dcm2bids-3.2.0.dist-info/entry_points.txt
dcm2bids-3.2.0.dist-info/top_level.txt
dcm2bids-3.2.0.dist-info/RECORD
