Metadata-Version: 2.1
Name: dcm2bids
Version: 3.2.0
Summary: Reorganising NIfTI files from dcm2niix into the Brain Imaging Data Structure
Maintainer: Arnaud Boré
Maintainer-email: arnaud.bore@gmail.com
License: GPLv3+
Project-URL: Documentation, https://unfmontreal.github.io/Dcm2Bids
Project-URL: Source Code, https://github.com/unfmontreal/Dcm2Bids
Platform: OS Independent
Classifier: Intended Audience :: Healthcare Industry
Classifier: Intended Audience :: Science/Research
Classifier: Operating System :: MacOS
Classifier: Operating System :: Microsoft :: Windows
Classifier: Operating System :: Unix
Classifier: Programming Language :: Python
Classifier: Programming Language :: Python :: 3.8
Classifier: Programming Language :: Python :: 3.9
Classifier: Programming Language :: Python :: 3.10
Classifier: Programming Language :: Python :: 3.11
Classifier: Topic :: Scientific/Engineering
Classifier: Topic :: Scientific/Engineering :: Bio-Informatics
Classifier: Topic :: Scientific/Engineering :: Medical Science Apps.
Requires-Python: >3.7
License-File: LICENSE.txt
Requires-Dist: packaging >=23.1
